hat/stc/statechart.py
hat/stc/runner.py
hat/stc/common.py
hat/stc/scxml.py
hat/stc/dot.py
hat/stc/__init__.py
hat_stc-0.7.3.dist-info/LICENSE
hat_stc-0.7.3.dist-info/METADATA
hat_stc-0.7.3.dist-info/WHEEL
hat_stc-0.7.3.dist-info/RECORD
