Metadata-Version: 2.1
Name: hat-stc
Version: 0.7.3
Summary: Hat statechart engine
License: Apache-2.0
Classifier: Programming Language :: Python :: 3
Classifier: License :: OSI Approved :: Apache Software License
Provides-Extra: dev
Requires-Dist: hat-aio ~=0.7.10
Requires-Dist: hat-doit ~=0.15.18; extra == 'dev'
Requires-Dist: sphinxcontrib-drawio >=0.0.17; extra == 'dev'
Requires-Python: >=3.10
Project-URL: Homepage, http://hat-open.com
Project-URL: Repository, https://github.com/hat-open/hat-stc.git
Project-URL: Documentation, http://hat-stc.hat-open.com
